LICENSE
LICENSE.txt
README.rst
setup.cfg
setup.py
thaistock/__init__.py
thaistock/stock.py
thaistock.egg-info/PKG-INFO
thaistock.egg-info/SOURCES.txt
thaistock.egg-info/dependency_links.txt
thaistock.egg-info/requires.txt
thaistock.egg-info/top_level.txt