Metadata-Version: 2.1
Name: thaistock
Version: 0.0.3
Summary: Thai stock data in The Stock Exchange of Thailand (SET) by Uncle Engineer
Home-page: https://github.com/UncleEngineer/ThaiStock
Author: Uncle Engineer
Author-email: loong.wissawakorn@gmail.com
License: MIT
Download-URL: https://github.com/UncleEngineer/ThaiStock/archive/refs/heads/main.zip
Keywords: Thai Stock,SET,Stock Exchange of Thailand,Uncle Engineer
Platform: UNKNOWN
Classifier: Development Status :: 3 - Alpha
Classifier: Intended Audience :: Education
Classifier: Topic :: Office/Business :: Financial
Classifier: License :: OSI Approved :: MIT License
Classifier: Programming Language :: Python :: 3
Classifier: Programming Language :: Python :: 3.4
Classifier: Programming Language :: Python :: 3.5
Classifier: Programming Language :: Python :: 3.6
Classifier: Programming Language :: Python :: 3.7
Classifier: Programming Language :: Python :: 3.8
Classifier: Programming Language :: Python :: 3.9
Classifier: Programming Language :: Python :: 3.10
License-File: LICENSE
License-File: LICENSE.txt
